<?xml version="1.0"?>
<object>
  <resourcetypes>
    <linkable>
      <element value="School"/>
      <element value="Division"/>
      <element value="Course"/>
    </linkable>
    <containsobjects>
      <element value="School"/>
      <element value="Division"/>
      <element value="Course"/>
    </containsobjects>
  </resourcetypes>
  <layout>
    <tablestyles>
      <element value="Document Table|documentTable"/>
    </tablestyles>
  </layout>
  <toolbar>
    <toolbar_media value="True" />
  </toolbar>
</object>
